{
  "positions": [
    {
      "fen": "r1bq1rk1/ppppnppp/5n2/2b1p3/2B1P3/2NP1N2/PPP2PPP/R1BQ1RK1 w - - 3 7",
      "stm": 0,
      "eval_score": 138,
      "depth": 12,
      "best_move": "f3e5",
      "game_result": 2,
      "material": 0,
      "piece_count": 32,
      "tau": 0.5
    },
    {
      "fen": "r1bq1rk1/ppppnppp/5n2/4N3/2BbP3/2NP4/PPP2PPP/R1BQ1RK1 w - - 1 8",
      "stm": 0,
      "eval_score": 142,
      "depth": 12,
      "best_move": "e5f3",
      "game_result": 2,
      "material": 1,
      "piece_count": 31,
      "tau": 0.5
    },
    {
      "fen": "r1bq1rk1/ppp1nppp/5n2/3P4/2B5/2PP1N2/P1P2PPP/R1BQ1RK1 b - - 0 10",
      "stm": 1,
      "eval_score": -135,
      "depth": 12,
      "best_move": "e7d5",
      "game_result": 2,
      "material": 2,
      "piece_count": 28,
      "tau": 0.45
    },
    {
      "fen": "r1bq1rk1/ppp2ppp/5n2/3n4/2B5/2PP1N2/P1P2PPP/R1BQ1RK1 w - - 0 11",
      "stm": 0,
      "eval_score": 144,
      "depth": 12,
      "best_move": "c1d2",
      "game_result": 2,
      "material": 1,
      "piece_count": 27,
      "tau": 0.45
    },
    {
      "fen": "r4rk1/ppp2ppp/3q1n2/3n1b2/2B5/2PP1N2/P1PB1PPP/R2QR1K1 w - - 4 13",
      "stm": 0,
      "eval_score": 146,
      "depth": 12,
      "best_move": "c4b3",
      "game_result": 2,
      "material": 1,
      "piece_count": 27,
      "tau": 0.45
    },
    {
      "fen": "r4rk1/ppp2ppp/3q1n2/3n1b2/8/1BPP1N2/P1PB1PPP/R2QR1K1 b - - 5 13",
      "stm": 1,
      "eval_score": -147,
      "depth": 12,
      "best_move": "a7a5",
      "game_result": 2,
      "material": 1,
      "piece_count": 27,
      "tau": 0.45
    },
    {
      "fen": "2r2rk1/ppp1nppp/3q1n2/5b2/2P5/1B1P1N2/P1PB1PPP/R2QR1K1 w - - 1 15",
      "stm": 0,
      "eval_score": 171,
      "depth": 12,
      "best_move": "d2c3",
      "game_result": 2,
      "material": 1,
      "piece_count": 27,
      "tau": 0.45
    },
    {
      "fen": "2r2rk1/ppp1nppp/3q1n2/5b2/2P5/1BBP1N2/P1P2PPP/R2QR1K1 b - - 2 15",
      "stm": 1,
      "eval_score": -168,
      "depth": 12,
      "best_move": "c7c5",
      "game_result": 2,
      "material": 1,
      "piece_count": 27,
      "tau": 0.45
    },
    {
      "fen": "2r2rk1/pp2nppp/3q1n2/2p2b2/2P5/1BBP1N2/P1P2PPP/R2QR1K1 w - - 0 16",
      "stm": 0,
      "eval_score": 163,
      "depth": 12,
      "best_move": "b3a4",
      "game_result": 2,
      "material": 1,
      "piece_count": 27,
      "tau": 0.45
    },
    {
      "fen": "2r2rk1/pp2nppp/3q1n2/2p2b2/B1P5/2BP1N2/P1P2PPP/R2QR1K1 b - - 1 16",
      "stm": 1,
      "eval_score": -165,
      "depth": 12,
      "best_move": "e7g6",
      "game_result": 2,
      "material": 1,
      "piece_count": 27,
      "tau": 0.45
    },
    {
      "fen": "2r2rk1/pp3ppp/3q1nn1/2p2b2/B1P5/2BP1N2/P1PQ1PPP/R3R1K1 b - - 3 17",
      "stm": 1,
      "eval_score": -167,
      "depth": 12,
      "best_move": "h7h6",
      "game_result": 2,
      "material": 1,
      "piece_count": 27,
      "tau": 0.45
    },
    {
      "fen": "2r2rk1/pp3pp1/3q1nnp/2p2b2/B1P5/2BP1N1P/P1PQ1PP1/R3R1K1 b - - 0 18",
      "stm": 1,
      "eval_score": -161,
      "depth": 12,
      "best_move": "f5d7",
      "game_result": 1,
      "material": 1,
      "piece_count": 27,
      "tau": 0.45
    },
    {
      "fen": "2r2rk1/pp1n1pp1/3q2np/2p5/2P5/2BP1N1P/P1PQ1PP1/R3R1K1 w - - 0 20",
      "stm": 0,
      "eval_score": 164,
      "depth": 12,
      "best_move": "d2e3",
      "game_result": 1,
      "material": 1,
      "piece_count": 25,
      "tau": 0.45
    },
    {
      "fen": "2r2rk1/pp1n1pp1/3q2np/2p5/2P5/2BPQN1P/P1P2PP1/R3R1K1 b - - 1 20",
      "stm": 1,
      "eval_score": -167,
      "depth": 12,
      "best_move": "d7f6",
      "game_result": 1,
      "material": 1,
      "piece_count": 25,
      "tau": 0.45
    },
    {
      "fen": "2r2rk1/p4pp1/1p1q1nnp/2p5/P1P5/2BPQ2P/2PN1PP1/R3R1K1 b - - 2 22",
      "stm": 1,
      "eval_score": -174,
      "depth": 12,
      "best_move": "f8e8",
      "game_result": 1,
      "material": 1,
      "piece_count": 25,
      "tau": 0.45
    },
    {
      "fen": "2r1r1k1/p4pp1/1p1q1nnp/2p5/P1P5/2BPQ2P/2PN1PP1/R3R1K1 w - - 3 23",
      "stm": 0,
      "eval_score": 181,
      "depth": 12,
      "best_move": "e3f3",
      "game_result": 1,
      "material": 1,
      "piece_count": 25,
      "tau": 0.45
    },
    {
      "fen": "2r1r1k1/p2n1pp1/1p1q2np/2p5/P1P1N3/2BP1Q1P/2P2PP1/R3R1K1 b - - 6 24",
      "stm": 1,
      "eval_score": -182,
      "depth": 12,
      "best_move": "d6c6",
      "game_result": 1,
      "material": 1,
      "piece_count": 25,
      "tau": 0.45
    },
    {
      "fen": "1qr3k1/p2nrpp1/1p4np/2p4P/P1P1N3/2BP1Q2/2P2PP1/R3R1K1 b - - 0 26",
      "stm": 1,
      "eval_score": -196,
      "depth": 12,
      "best_move": "g6e5",
      "game_result": 1,
      "material": 1,
      "piece_count": 25,
      "tau": 0.45
    },
    {
      "fen": "1q2r1k1/p2nrpp1/1p5p/2p1n2P/P1P1NQ2/2BP4/2P2PP1/R3R1K1 w - - 3 28",
      "stm": 0,
      "eval_score": 185,
      "depth": 12,
      "best_move": "e4g3",
      "game_result": 1,
      "material": 1,
      "piece_count": 25,
      "tau": 0.45
    },
    {
      "fen": "1q2r1k1/p2nrpp1/1p5p/2p1n2P/P1P2Q2/2BP2N1/2P2PP1/R3R1K1 b - - 4 28",
      "stm": 1,
      "eval_score": -184,
      "depth": 12,
      "best_move": "e7e6",
      "game_result": 1,
      "material": 1,
      "piece_count": 25,
      "tau": 0.45
    },
    {
      "fen": "1q3r1k/p2n4/1p2r3/2p1N2p/P1P5/3P3Q/2P2PP1/R3R1K1 b - - 0 35",
      "stm": 1,
      "eval_score": -271,
      "depth": 12,
      "best_move": "e6e5",
      "game_result": 1,
      "material": 2,
      "piece_count": 20,
      "tau": 0.4
    },
    {
      "fen": "r1b1k1nr/pppp1ppp/1q6/4P3/3Q4/8/PPP2PPP/RN2KB1R w KQkq - 1 10",
      "stm": 0,
      "eval_score": 18,
      "depth": 12,
      "best_move": "d4c3",
      "game_result": 2,
      "material": 0,
      "piece_count": 26,
      "tau": 0.4
    },
    {
      "fen": "r1b1k1nr/pppp1ppp/1q6/4P3/8/2Q5/PPP2PPP/RN2KB1R b KQkq - 2 10",
      "stm": 1,
      "eval_score": -16,
      "depth": 12,
      "best_move": "g8e7",
      "game_result": 2,
      "material": 0,
      "piece_count": 26,
      "tau": 0.4
    },
    {
      "fen": "rnb1k2r/ppp1qpbp/3p1np1/P2Pp3/2B1P3/2N2N1P/1PP2PP1/R1BQK2R b KQkq - 0 9",
      "stm": 1,
      "eval_score": -100,
      "depth": 12,
      "best_move": "c7c6",
      "game_result": 2,
      "material": 0,
      "piece_count": 32,
      "tau": 0.5
    },
    {
      "fen": "rnb2rk1/ppp1qpbp/3p1np1/P2Pp3/2B1P3/2N2N1P/1PP2PP1/R1BQ1RK1 b - - 2 10",
      "stm": 1,
      "eval_score": -92,
      "depth": 12,
      "best_move": "c7c6",
      "game_result": 2,
      "material": 0,
      "piece_count": 32,
      "tau": 0.5
    },
    {
      "fen": "rnb2rk1/pp2qpbp/2pp1np1/P2Pp3/2B1P3/2N2N1P/1PP2PP1/R1BQ1RK1 w - - 0 11",
      "stm": 0,
      "eval_score": 88,
      "depth": 12,
      "best_move": "c1g5",
      "game_result": 2,
      "material": 0,
      "piece_count": 32,
      "tau": 0.5
    },
    {
      "fen": "rnb2rk1/pp2qpb1/2pp1npp/P2Pp3/2B1P3/2N1BN1P/1PP2PP1/R2Q1RK1 b - - 1 12",
      "stm": 1,
      "eval_score": -80,
      "depth": 12,
      "best_move": "c6d5",
      "game_result": 2,
      "material": 0,
      "piece_count": 32,
      "tau": 0.5
    },
    {
      "fen": "rnb2rk1/pp2qpb1/3p1npp/P2Np3/2B1P3/4BN1P/1PP2PP1/R2Q1RK1 b - - 0 13",
      "stm": 1,
      "eval_score": -72,
      "depth": 12,
      "best_move": "f6d5",
      "game_result": 2,
      "material": 0,
      "piece_count": 30,
      "tau": 0.5
    },
    {
      "fen": "rn3rk1/pp2qpb1/3pb1pp/P2Bp3/4P3/4BN1P/1PP2PP1/R2Q1RK1 w - - 1 15",
      "stm": 0,
      "eval_score": 78,
      "depth": 12,
      "best_move": "a1a3",
      "game_result": 2,
      "material": 0,
      "piece_count": 28,
      "tau": 0.4
    },
    {
      "fen": "1r1q1rk1/pB1n1pb1/P5pp/4p3/8/3QBN1P/1PP2PP1/3R2K1 b - - 0 21",
      "stm": 1,
      "eval_score": -265,
      "depth": 12,
      "best_move": "d8f6",
      "game_result": 2,
      "material": -1,
      "piece_count": 23,
      "tau": 0.35
    },
    {
      "fen": "3r1rk1/BB1n1pb1/P4qpp/4p3/8/3Q1N1P/1PP2PP1/3R2K1 w - - 1 23",
      "stm": 0,
      "eval_score": 250,
      "depth": 12,
      "best_move": "d3b5",
      "game_result": 2,
      "material": 0,
      "piece_count": 22,
      "tau": 0.35
    },
    {
      "fen": "3r1rk1/BB1n1pb1/P5pp/1Q2q3/1P1Np3/7P/2P2PP1/3R2K1 b - - 0 25",
      "stm": 1,
      "eval_score": -281,
      "depth": 12,
      "best_move": "f8e8",
      "game_result": 2,
      "material": 0,
      "piece_count": 22,
      "tau": 0.35
    },
    {
      "fen": "1B1rr1k1/1B1n1pb1/P5pp/1Q2q3/1P1Np3/7P/2P2PP1/3R2K1 b - - 2 26",
      "stm": 1,
      "eval_score": 185,
      "depth": 12,
      "best_move": "d8b8",
      "game_result": 2,
      "material": 0,
      "piece_count": 22,
      "tau": 0.35
    },
    {
      "fen": "1r2r1k1/1B1n1pb1/P5pp/4Q3/1P1Np3/7P/2P2PP1/3R2K1 b - - 0 27",
      "stm": 1,
      "eval_score": 207,
      "depth": 12,
      "best_move": "d7e5",
      "game_result": 2,
      "material": 6,
      "piece_count": 20,
      "tau": 0.3
    },
    {
      "fen": "1r2r1k1/1B3pb1/P5pp/4n3/1P1Np3/7P/2P2PP1/3R2K1 w - - 0 28",
      "stm": 0,
      "eval_score": -210,
      "depth": 12,
      "best_move": "d4b5",
      "game_result": 2,
      "material": -3,
      "piece_count": 19,
      "tau": 0.25
    },
    {
      "fen": "1r2r1k1/1B3pb1/Pn1R2pp/1N6/1P2p3/7P/2P2PP1/6K1 b - - 5 30",
      "stm": 1,
      "eval_score": 188,
      "depth": 12,
      "best_move": "b6c4",
      "game_result": 2,
      "material": -3,
      "piece_count": 19,
      "tau": 0.25
    },
    {
      "fen": "1r2r1k1/1B3pb1/P1R3pp/1N6/1Pn5/4P2P/2P3P1/6K1 b - - 0 32",
      "stm": 1,
      "eval_score": 219,
      "depth": 12,
      "best_move": "c4e3",
      "game_result": 1,
      "material": -2,
      "piece_count": 18,
      "tau": 0.25
    },
    {
      "fen": "1r2r1k1/1B3pb1/P1R3pp/1N6/1P6/2P1n2P/6P1/6K1 b - - 0 33",
      "stm": 1,
      "eval_score": 241,
      "depth": 12,
      "best_move": "e3d5",
      "game_result": 1,
      "material": -3,
      "piece_count": 17,
      "tau": 0.25
    },
    {
      "fen": "1r2r1k1/1B3pb1/P1R3pp/1N1n4/1P6/2P4P/5KP1/8 b - - 2 34",
      "stm": 1,
      "eval_score": 230,
      "depth": 12,
      "best_move": "e8e7",
      "game_result": 1,
      "material": -3,
      "piece_count": 17,
      "tau": 0.25
    },
    {
      "fen": "1r4k1/1B2rpb1/P1R3pp/1N1n4/1P6/2P4P/5KP1/8 w - - 3 35",
      "stm": 0,
      "eval_score": -240,
      "depth": 12,
      "best_move": "c6c5",
      "game_result": 1,
      "material": -3,
      "piece_count": 17,
      "tau": 0.25
    },
    {
      "fen": "1r4k1/1B2rpb1/Pn4pp/1NR5/1P6/2P4P/5KP1/8 w - - 5 36",
      "stm": 0,
      "eval_score": -256,
      "depth": 12,
      "best_move": "c5c6",
      "game_result": 1,
      "material": -3,
      "piece_count": 17,
      "tau": 0.25
    },
    {
      "fen": "r1bqk2r/ppp2pp1/3p1n1p/n3p3/P3P3/2NPPN2/BPP3PP/R2QK2R b KQkq - 2 9",
      "stm": 1,
      "eval_score": -3,
      "depth": 12,
      "best_move": "a5c6",
      "game_result": 1,
      "material": 0,
      "piece_count": 30,
      "tau": 0.5
    },
    {
      "fen": "r1bqk2r/ppp2pp1/2np3p/3Np3/P3P3/4PN2/BPP3PP/R2QK2R b KQkq - 0 11",
      "stm": 1,
      "eval_score": -355,
      "depth": 12,
      "best_move": "c6e7",
      "game_result": 1,
      "material": 2,
      "piece_count": 28,
      "tau": 0.45
    },
    {
      "fen": "r1bqk2r/1pp2pp1/2np3p/p2Np3/P3P3/4PN2/BPP3PP/R2QK2R w KQkq - 0 12",
      "stm": 0,
      "eval_score": 321,
      "depth": 12,
      "best_move": "f3d2",
      "game_result": 1,
      "material": 2,
      "piece_count": 28,
      "tau": 0.45
    },
    {
      "fen": "r1bqk2r/1pp2pp1/2np3p/p2Np3/P3P3/4PN1P/BPP3P1/R2QK2R b KQkq - 0 12",
      "stm": 1,
      "eval_score": -316,
      "depth": 12,
      "best_move": "e8g8",
      "game_result": 1,
      "material": 2,
      "piece_count": 28,
      "tau": 0.45
    },
    {
      "fen": "rnbq1rk1/1pp2pp1/3p3p/p2Np3/P3P3/4PN1P/BPP3P1/R2Q1RK1 w - - 3 14",
      "stm": 0,
      "eval_score": 315,
      "depth": 12,
      "best_move": "f3d2",
      "game_result": 1,
      "material": 2,
      "piece_count": 28,
      "tau": 0.45
    },
    {
      "fen": "rn1q1rk1/1pp2pp1/3p3p/p3p3/P3P3/2N1PN1P/bPP1Q1P1/R4RK1 w - - 0 16",
      "stm": 0,
      "eval_score": 337,
      "depth": 12,
      "best_move": "a1a2",
      "game_result": 1,
      "material": -1,
      "piece_count": 27,
      "tau": 0.45
    },
    {
      "fen": "rn1q1rk1/1pp2pp1/3p3p/p3p3/P3P3/4PN1P/NPP1Q1P1/R4RK1 b - - 0 16",
      "stm": 1,
      "eval_score": -341,
      "depth": 12,
      "best_move": "d8e7",
      "game_result": 1,
      "material": 2,
      "piece_count": 26,
      "tau": 0.45
    },
    {
      "fen": "r2q1rk1/1p3pp1/n1pp3p/p3p3/P3P3/2N1PN1P/1PP1Q1P1/R4RK1 w - - 0 18",
      "stm": 0,
      "eval_score": 354,
      "depth": 12,
      "best_move": "f3d2",
      "game_result": 0,
      "material": 2,
      "piece_count": 26,
      "tau": 0.45
    },
    {
      "fen": "r2q1rk1/5pp1/1p1p3p/pQn1N3/P3P3/4P2P/1PP3P1/3R1RK1 b - - 0 21",
      "stm": 1,
      "eval_score": -45,
      "depth": 12,
      "best_move": "a8c8",
      "game_result": 0,
      "material": 1,
      "piece_count": 23,
      "tau": 0.4
    },
    {
      "fen": "2r2rk1/5pp1/1p1p3p/pQn5/P1N1P2q/4P3/1PP3P1/3R1RK1 b - - 1 23",
      "stm": 1,
      "eval_score": 38,
      "depth": 12,
      "best_move": "c5e4",
      "game_result": 2,
      "material": 0,
      "piece_count": 22,
      "tau": 0.4
    },
    {
      "fen": "r3kbnr/pppq1pp1/2n1p2p/5bP1/Q1pP4/5N2/PP2PPBP/RNB1K2R w KQkq - 4 8",
      "stm": 0,
      "eval_score": -86,
      "depth": 12,
      "best_move": "a4c4",
      "game_result": 2,
      "material": -1,
      "piece_count": 31,
      "tau": 0.5
    },
    {
      "fen": "2kr1bnr/pppq1pp1/2n1p2p/5bP1/2QP4/5N2/PP2PPBP/RNB1K2R w KQ - 1 9",
      "stm": 0,
      "eval_score": -86,
      "depth": 12,
      "best_move": "g5h6",
      "game_result": 2,
      "material": 0,
      "piece_count": 30,
      "tau": 0.5
    },
    {
      "fen": "2kr1bnr/pppq1pp1/4p3/5bN1/1nQP4/4B3/PP2PPBP/RN2K2R w KQ - 1 11",
      "stm": 0,
      "eval_score": -114,
      "depth": 12,
      "best_move": "b1a3",
      "game_result": 2,
      "material": 0,
      "piece_count": 28,
      "tau": 0.5
    },
    {
      "fen": "2kr1bnr/pppq1pp1/4p3/5bN1/1nQP4/N3B3/PP2PPBP/R3K2R b KQ - 2 11",
      "stm": 1,
      "eval_score": 119,
      "depth": 12,
      "best_move": "b4d5",
      "game_result": 2,
      "material": 0,
      "piece_count": 28,
      "tau": 0.5
    },
    {
      "fen": "2kr2nr/pppq2p1/4pp2/2bn1b2/2QP4/4B3/PPN1PPBP/R3KR2 w Q - 0 16",
      "stm": 0,
      "eval_score": -137,
      "depth": 12,
      "best_move": "c4c5",
      "game_result": 2,
      "material": -3,
      "piece_count": 27,
      "tau": 0.45
    },
    {
      "fen": "2kr2nr/pppq2p1/4pp2/2Pn1b2/2Q5/4B3/PPN1PPBP/R3KR2 b Q - 0 16",
      "stm": 1,
      "eval_score": 276,
      "depth": 12,
      "best_move": "d5e3",
      "game_result": 2,
      "material": 0,
      "piece_count": 26,
      "tau": 0.45
    },
    {
      "fen": "1r1qkb1r/pp3ppp/4pn2/2pp1b2/2PP4/2N1P3/PP3PPP/R2QKBNR w KQk - 0 7",
      "stm": 0,
      "eval_score": 59,
      "depth": 12,
      "best_move": "d1a4",
      "game_result": 2,
      "material": 0,
      "piece_count": 30,
      "tau": 0.45
    },
    {
      "fen": "1r1qkb1r/pp1n1ppp/4p3/2pp1b2/Q1PP4/2N1P3/PP3PPP/R3KBNR w KQk - 2 8",
      "stm": 0,
      "eval_score": 65,
      "depth": 12,
      "best_move": "c4d5",
      "game_result": 2,
      "material": 0,
      "piece_count": 30,
      "tau": 0.45
    },
    {
      "fen": "1r1qkb1r/pp1n1ppp/4p3/2pP1b2/Q2P4/2N1P3/PP3PPP/R3KBNR b KQk - 0 8",
      "stm": 1,
      "eval_score": -67,
      "depth": 12,
      "best_move": "e6d5",
      "game_result": 0,
      "material": 1,
      "piece_count": 29,
      "tau": 0.45
    },
    {
      "fen": "1r1qkb1r/pp1n1ppp/8/2pN4/Q2Pb3/4P3/PP3PPP/R3KBNR w KQk - 1 10",
      "stm": 0,
      "eval_score": 68,
      "depth": 12,
      "best_move": "d5c3",
      "game_result": 0,
      "material": 1,
      "piece_count": 27,
      "tau": 0.45
    },
    {
      "fen": "1r1q1rk1/pp1nbppp/8/2p5/Q2PN3/4P3/PP3PPP/R3KBNR w KQ - 1 12",
      "stm": 0,
      "eval_score": 344,
      "depth": 12,
      "best_move": "g1f3",
      "game_result": 0,
      "material": 4,
      "piece_count": 26,
      "tau": 0.45
    },
    {
      "fen": "1r1q1rk1/pp1nbppp/8/2p5/3PN3/4P3/PP3PPP/R2QKBNR b KQ - 2 12",
      "stm": 1,
      "eval_score": -239,
      "depth": 12,
      "best_move": "c5d4",
      "game_result": 0,
      "material": 4,
      "piece_count": 26,
      "tau": 0.45
    },
    {
      "fen": "1r3rk1/pp1nbppp/8/q7/3pN1P1/4P3/PP3P1P/R2QKBNR w KQ - 1 14",
      "stm": 0,
      "eval_score": 120,
      "depth": 12,
      "best_move": "e1e2",
      "game_result": 0,
      "material": 3,
      "piece_count": 25,
      "tau": 0.75
    },
    {
      "fen": "1r3rk1/pp1nb1pp/8/q4P2/3pN3/4P3/PP2KP1P/R2Q1BNR b - - 0 15",
      "stm": 1,
      "eval_score": -114,
      "depth": 12,
      "best_move": "a5b5",
      "game_result": 0,
      "material": 4,
      "piece_count": 24,
      "tau": 0.45
    },
    {
      "fen": "1r3rk1/pp1nb1pp/8/1q3P2/3pN3/4P3/PP2KP1P/R2Q1BNR w - - 1 16",
      "stm": 0,
      "eval_score": 134,
      "depth": 12,
      "best_move": "e2e1",
      "game_result": 0,
      "material": 4,
      "piece_count": 24,
      "tau": 0.75
    },
    {
      "fen": "rnbq1rk1/ppp1bpp1/4pn1p/3p4/2PP3B/2N2N2/PP2PPPP/R2QKB1R w KQ - 2 7",
      "stm": 0,
      "eval_score": 39,
      "depth": 12,
      "best_move": "e2e3",
      "game_result": 0,
      "material": 0,
      "piece_count": 32,
      "tau": 0.5
    },
    {
      "fen": "rnbq1rk1/p1p1bpp1/1p2pn1p/3p4/2PP3B/2N1PN2/PP3PPP/R2QKB1R w KQ - 0 8",
      "stm": 0,
      "eval_score": 27,
      "depth": 12,
      "best_move": "f1e2",
      "game_result": 0,
      "material": 0,
      "piece_count": 32,
      "tau": 0.5
    },
    {
      "fen": "rnbq1rk1/p1p1bp2/1p2pn1p/3p2p1/2PP3B/2N1PN2/PP2BPPP/R2QK2R w KQ - 0 9",
      "stm": 0,
      "eval_score": 97,
      "depth": 12,
      "best_move": "h4g3",
      "game_result": 0,
      "material": 0,
      "piece_count": 32,
      "tau": 0.5
    },
    {
      "fen": "rnbq1rk1/p1p1bp2/1p2pn1p/3p2p1/2PP4/2N1PNB1/PP2BPPP/R2QK2R b KQ - 1 9",
      "stm": 1,
      "eval_score": -94,
      "depth": 12,
      "best_move": "b8d7",
      "game_result": 0,
      "material": 0,
      "piece_count": 32,
      "tau": 0.5
    },
    {
      "fen": "r1bq1rk1/p1pnbp2/1p2pn2/7p/2pPP1pP/2N3B1/PP1NBPP1/R2Q1K1R b - - 0 13",
      "stm": 1,
      "eval_score": 11,
      "depth": 12,
      "best_move": "c8b7",
      "game_result": 0,
      "material": -1,
      "piece_count": 31,
      "tau": 0.5
    },
    {
      "fen": "r2q1rk1/pbpnbp2/1p2pn2/7p/2pPP1pP/2N3B1/PP1NBPP1/R2Q1K1R w - - 1 14",
      "stm": 0,
      "eval_score": 7,
      "depth": 12,
      "best_move": "f2f3",
      "game_result": 0,
      "material": -1,
      "piece_count": 31,
      "tau": 0.5
    },
    {
      "fen": "r2q1r1k/pbpnbp2/1p2pn2/7p/2NPP1pP/2N2PB1/PP2B1P1/R2Q1K1R b - - 0 15",
      "stm": 1,
      "eval_score": -66,
      "depth": 12,
      "best_move": "f8g8",
      "game_result": 0,
      "material": 0,
      "piece_count": 30,
      "tau": 0.5
    },
    {
      "fen": "r2q2rk/pbpnbp2/1p2pn2/7p/2NPP1pP/2N2PB1/PP2B1P1/R2Q2KR b - - 2 16",
      "stm": 1,
      "eval_score": 388,
      "depth": 12,
      "best_move": "g4f3",
      "game_result": 0,
      "material": 0,
      "piece_count": 30,
      "tau": 0.5
    },
    {
      "fen": "r2q3k/pbp1bpr1/1p2pn2/7p/1PNPP1nP/2N3BR/P3p1P1/2R1Q1K1 w - - 1 21",
      "stm": 0,
      "eval_score": -389,
      "depth": 12,
      "best_move": "d4d5",
      "game_result": 0,
      "material": -4,
      "piece_count": 28,
      "tau": 0.5
    },
    {
      "fen": "r2q3k/pbp1bpr1/1p3n2/3Pp2p/1PN1P1nP/2N3BR/P3p1P1/2R1Q1K1 w - - 0 22",
      "stm": 0,
      "eval_score": -398,
      "depth": 12,
      "best_move": "c4d2",
      "game_result": 0,
      "material": -4,
      "piece_count": 28,
      "tau": 0.5
    },
    {
      "fen": "r2q3k/4bpr1/1p1p4/pP1bp2p/6nP/6BR/P2NQ1P1/2R3K1 w - a6 0 28",
      "stm": 0,
      "eval_score": -372,
      "depth": 12,
      "best_move": "b5a6",
      "game_result": 0,
      "material": -5,
      "piece_count": 23,
      "tau": 0.4
    },
    {
      "fen": "r2q3k/4bpr1/Pp1p4/3bp2p/6nP/6BR/P2NQ1P1/2R3K1 b - - 0 28",
      "stm": 1,
      "eval_score": 395,
      "depth": 12,
      "best_move": "b6b5",
      "game_result": 0,
      "material": -4,
      "piece_count": 22,
      "tau": 0.4
    },
    {
      "fen": "r3k1nr/ppp2ppp/2nb4/8/1P2P3/2NB1b2/P1P2P1P/R1B1K1R1 w Qkq - 2 11",
      "stm": 0,
      "eval_score": -321,
      "depth": 12,
      "best_move": "c1b2",
      "game_result": 0,
      "material": -3,
      "piece_count": 25,
      "tau": 0.35
    },
    {
      "fen": "r3k1nr/ppp2ppp/2nb4/1N6/1P2P3/3B1b2/P1P2P1P/R1B1K1R1 b Qkq - 3 11",
      "stm": 1,
      "eval_score": 360,
      "depth": 12,
      "best_move": "d6e5",
      "game_result": 0,
      "material": -3,
      "piece_count": 25,
      "tau": 0.35
    },
    {
      "fen": "r1b1kb1r/ppp2p1p/2n1Qnp1/3p4/PP1P1P2/2P5/6PP/RNB1KBNR b KQkq - 0 10",
      "stm": 1,
      "eval_score": 38,
      "depth": 12,
      "best_move": "c8e6",
      "game_result": 0,
      "material": 9,
      "piece_count": 29,
      "tau": 0.75
    },
    {
      "fen": "r3kb1r/1pp2p1p/p1n1bnp1/P2p4/1P1P1P2/2P2N2/6PP/RNB1KB1R b KQkq - 1 12",
      "stm": 1,
      "eval_score": 44,
      "depth": 12,
      "best_move": "f8d6",
      "game_result": 0,
      "material": 0,
      "piece_count": 28,
      "tau": 0.4
    },
    {
      "fen": "r3k2r/1pp2p1p/p1nbbnp1/P2p4/1P1P1P2/2P2N2/6PP/RNB1KB1R w KQkq - 2 13",
      "stm": 0,
      "eval_score": -40,
      "depth": 12,
      "best_move": "f1d3",
      "game_result": 0,
      "material": 0,
      "piece_count": 28,
      "tau": 0.4
    },
    {
      "fen": "r3k2r/1pp2p1p/p1nbbnp1/P2p4/1P1P1P2/2PB1N2/6PP/RNB1K2R b KQkq - 3 13",
      "stm": 1,
      "eval_score": 42,
      "depth": 12,
      "best_move": "c6e7",
      "game_result": 0,
      "material": 0,
      "piece_count": 28,
      "tau": 0.4
    },
    {
      "fen": "r3k2r/1pp1np1p/p2bbnp1/P2p4/1P1P1P2/2PB1N2/6PP/RNB1K2R w KQkq - 4 14",
      "stm": 0,
      "eval_score": -36,
      "depth": 12,
      "best_move": "e1g1",
      "game_result": 0,
      "material": 0,
      "piece_count": 28,
      "tau": 0.4
    },
    {
      "fen": "4r1k1/5p1p/ppp3pb/P1Pp4/1P1P4/2R2NP1/7P/6K1 w - - 0 27",
      "stm": 0,
      "eval_score": 274,
      "depth": 12,
      "best_move": "a5b6",
      "game_result": 0,
      "material": -1,
      "piece_count": 19,
      "tau": 0.15
    },
    {
      "fen": "4r1k1/5p1p/p1p3pb/P1Pp4/3P4/3R1NP1/7P/6K1 b - - 0 28",
      "stm": 1,
      "eval_score": 60,
      "depth": 12,
      "best_move": "h6e3",
      "game_result": 0,
      "material": -1,
      "piece_count": 17,
      "tau": 0.15
    },
    {
      "fen": "4r1k1/5p2/p1p3p1/P1Pp3p/3P4/3RbNP1/7P/5K2 w - - 0 30",
      "stm": 0,
      "eval_score": -45,
      "depth": 12,
      "best_move": "h2h4",
      "game_result": 0,
      "material": -1,
      "piece_count": 17,
      "tau": 0.15
    },
    {
      "fen": "6k1/5p2/p1p3p1/P1Pp3p/3Pr2P/3RbNP1/8/5K2 w - - 1 31",
      "stm": 0,
      "eval_score": -30,
      "depth": 12,
      "best_move": "d3b3",
      "game_result": 0,
      "material": -1,
      "piece_count": 17,
      "tau": 0.15
    }
  ],
  "stats": {
    "total_positions": 89,
    "avg_eval": 0.53,
    "avg_tau": 0.4281,
    "white_wins": 35,
    "black_wins": 32,
    "draws": 22
  },
  "timestamp": "2026-04-14 18:06:32"
}